tfnz
