Metadata-Version: 1.1
Name: tfnz
Version: 1.3.0
Summary: SDK for 20ft.nz
Home-page: https://20ft.nz
Author: David Preece
Author-email: davep@20ft.nz
License: BSD
Keywords: container containers PaaS docker orchestration 20ft 20ft.nz
Platform: UNKNOWN
Classifier: Development Status :: 5 - Production/Stable
Classifier: Intended Audience :: Developers
Classifier: Intended Audience :: Information Technology
Classifier: Intended Audience :: System Administrators
Classifier: License :: OSI Approved :: BSD License
Classifier: Natural Language :: English
Classifier: Topic :: Software Development :: Testing
Classifier: Topic :: System :: Software Distribution
Classifier: Programming Language :: Python :: 3.4
Classifier: Programming Language :: Python :: 3.5
Classifier: Programming Language :: Python :: 3.6
